{
  "users": [
    {
      "id": "ee24",
      "name": "Ahmad Zaini",
      "email": "ahmadpacen@gmail.com",
      "password": "123"
    },
    {
      "id": "c1c7",
      "name": "Synthia",
      "email": "syntia@mail.com",
      "password": "1122"
    }
  ],
  "products": [
    {
      "id": 1,
      "name": "Jamu Kunyit Asem",
      "price": 15000,
      "image": "https://asset.kompas.com/crops/YdCxZWTFzecZK5U9uL-_uae7VgA=/24x0:867x562/1200x800/data/photo/2021/03/02/603e41b8eaf6b.jpg",
      "Filter": "Jamu"
    },
    {
      "id": 2,
      "name": "Jamu Beras Kencur",
      "price": 12000,
      "image": "https://asset.kompas.com/crops/BHUd5qd_lpa9Ae-Zc1I-oAJ6g1k=/0x0:490x327/1200x800/data/photo/2023/05/01/644f83344bd06.png",
      "Filter": "Jamu"
    },
    {
      "id": 3,
      "name": "Jamu Temulawak",
      "price": 16000,
      "image": "https://asset.kompas.com/crops/BHUd5qd_lpa9Ae-Zc1I-oAJ6g1k=/0x0:490x327/1200x800/data/photo/2023/05/01/644f83344bd06.png",
      "Filter": "Jamu"
    }
  ],
  "histories": []
}
